setup.cfg
setup.py
pithytools/__init__.py
pithytools.egg-info/PKG-INFO
pithytools.egg-info/SOURCES.txt
pithytools.egg-info/dependency_links.txt
pithytools.egg-info/top_level.txt
pithytools/bin/__init__.py
pithytools/bin/conv_img.py
pithytools/bin/count_ext.py
pithytools/bin/crawl.py
pithytools/bin/digest.py
pithytools/bin/html_check.py
pithytools/bin/html_esc.py
pithytools/bin/html_extract.py
pithytools/bin/html_view.py
pithytools/bin/json_schema.py
pithytools/bin/lc_ext.py
pithytools/bin/lc_name.py
pithytools/bin/oq.py
pithytools/bin/pack.py
pithytools/bin/pat.py
pithytools/bin/py_lldb.py
pithytools/bin/py_profile.py
pithytools/bin/same_same.py
pithytools/bin/serve_dir.py
pithytools/bin/sum.py
pithytools/bin/time_runs.py
pithytools/bin/timesheet.py